<annotation>
	<folder>train</folder>
	<filename>Buoi_00001.jpg</filename>
	<path>d:\ThiGiacMay\NamHoc_2022_2023_1\NhanDangTraiCay\Tensorflow\workspace\images\train\Buoi_00001.jpg</path>
	<source>
		<database>Unknown</database>
	</source>
	<size>
		<width>292</width>
		<height>261</height>
		<depth>3</depth>
	</size>
	<segmented>0</segmented>
	<object>
		<name>Buoi</name>
		<pose>Unspecified</pose>
		<truncated>0</truncated>
		<difficult>0</difficult>
		<bndbox>
			<xmin>63</xmin>
			<ymin>11</ymin>
			<xmax>225</xmax>
			<ymax>156</ymax>
		</bndbox>
	</object>
</annotation>
